<?xml version="1.0"?>
<ArrayOfKomentar xmlns:xsi="http://www.w3.org/2001/XMLSchema-instance" xmlns:xsd="http://www.w3.org/2001/XMLSchema">
  <Komentar>
    <Vezbac>nebojsa</Vezbac>
    <FitnesCentar>Sparta</FitnesCentar>
    <Ocena>5</Ocena>
    <Tekst>Dobar</Tekst>
    <Odobren>true</Odobren>
    <Obradjen>true</Obradjen>
  </Komentar>
  <Komentar>
    <Vezbac>nebojsa</Vezbac>
    <FitnesCentar>Sparta</FitnesCentar>
    <Ocena>4</Ocena>
    <Tekst>Vrlo Dobro</Tekst>
    <Odobren>true</Odobren>
    <Obradjen>true</Obradjen>
  </Komentar>
</ArrayOfKomentar>